didis/batch.py
didis/didis.py
didis-0.0.30.dist-info/METADATA
didis-0.0.30.dist-info/WHEEL
didis-0.0.30.dist-info/entry_points.txt
didis-0.0.30.dist-info/top_level.txt
didis-0.0.30.dist-info/RECORD
