Metadata-Version: 2.4
Name: didis
Version: 0.0.30
Summary: DIDIS - Desy ITk Database Interaction Script
Home-page: https://gitlab.cern.ch/mcaspar/didis
Author: Maximilian Caspar
Author-email: maximilian.caspar@desy.de
License: MIT
Classifier: Programming Language :: Python :: 3
Classifier: Programming Language :: Python :: 3.7
Requires-Dist: loguru
Requires-Dist: argh
Requires-Dist: itkdb
Requires-Dist: pyyaml
Requires-Dist: openpyxl
Requires-Dist: pandas
Requires-Dist: docxtpl
Requires-Dist: docx2pdf
Dynamic: author
Dynamic: author-email
Dynamic: classifier
Dynamic: description
Dynamic: description-content-type
Dynamic: home-page
Dynamic: license
Dynamic: requires-dist
Dynamic: summary
